jupyter_offlinenotebook/__init__.py
jupyter_offlinenotebook/description.yaml
jupyter_offlinenotebook/etc/offlinenotebook_jpserverextension.json
jupyter_offlinenotebook/etc/offlinenotebook_nbextension.json
jupyter_offlinenotebook/etc/offlinenotebook_nbserverextension.json
jupyter_offlinenotebook/static/main.js
jupyter_offlinenotebook/static/jslib/offlinenotebook.js
jupyter_offlinenotebook/static/jslib/offlinenotebook.js.map
jupyter_offlinenotebook/static/lab/package.json
jupyter_offlinenotebook/static/lab/static/118.e6106e1fe10a05c1e5d3.js
jupyter_offlinenotebook/static/lab/static/154.949df7a622cd607c71df.js
jupyter_offlinenotebook/static/lab/static/665.fd294e59a544ff18521c.js
jupyter_offlinenotebook/static/lab/static/692.16520871d64a9f401c70.js
jupyter_offlinenotebook/static/lab/static/692.16520871d64a9f401c70.js.LICENSE.txt
jupyter_offlinenotebook/static/lab/static/remoteEntry.7e9ff55611d344fb44ca.js
jupyter_offlinenotebook/static/lab/static/style.js
jupyter_offlinenotebook/static/lab/static/third-party-licenses.json
jupyter_offlinenotebook-0.3.2.data/data/etc/jupyter/jupyter_notebook_config.d/offlinenotebook_nbserverextension.json
jupyter_offlinenotebook-0.3.2.data/data/etc/jupyter/jupyter_server_config.d/offlinenotebook_jpserverextension.json
jupyter_offlinenotebook-0.3.2.data/data/etc/jupyter/nbconfig/notebook.d/offlinenotebook_nbextension.json
jupyter_offlinenotebook-0.3.2.data/data/share/jupyter/labextensions/jupyter-offlinenotebook/package.json
jupyter_offlinenotebook-0.3.2.data/data/share/jupyter/labextensions/jupyter-offlinenotebook/static/118.e6106e1fe10a05c1e5d3.js
jupyter_offlinenotebook-0.3.2.data/data/share/jupyter/labextensions/jupyter-offlinenotebook/static/154.949df7a622cd607c71df.js
jupyter_offlinenotebook-0.3.2.data/data/share/jupyter/labextensions/jupyter-offlinenotebook/static/665.fd294e59a544ff18521c.js
jupyter_offlinenotebook-0.3.2.data/data/share/jupyter/labextensions/jupyter-offlinenotebook/static/692.16520871d64a9f401c70.js
jupyter_offlinenotebook-0.3.2.dist-info/licenses/LICENSE
jupyter_offlinenotebook-0.3.2.dist-info/METADATA
jupyter_offlinenotebook-0.3.2.dist-info/WHEEL
jupyter_offlinenotebook-0.3.2.dist-info/top_level.txt
jupyter_offlinenotebook-0.3.2.dist-info/RECORD
